LICENSE.txt
MANIFEST.in
README
setup.py
podparser/__init__.py
podparser/checker.py
podparser/directory.py
podparser/fetcher.py
podparser/parser.py
podparser.egg-info/PKG-INFO
podparser.egg-info/SOURCES.txt
podparser.egg-info/dependency_links.txt
podparser.egg-info/entry_points.txt
podparser.egg-info/requires.txt
podparser.egg-info/top_level.txt
podparser/db/__init__.py
podparser/db/connection.py
podparser/etc/DJVU.xsl
podparser/etc/schema.sql
podparser/geo/__init__.py
podparser/geo/encoder.py