Metadata-Version: 1.1
Name: podparser
Version: 0.4
Summary: Post Office Directory Parser
Home-page: https://github.com/gmh04/podparser
Author: George Hamilton
Author-email: george.hamilton@ed.ac.uk
License: GPL
Keywords: post-office pod directory geneology history scotland
Platform: UNKNOWN
Classifier: Development Status :: 4 - Beta
Classifier: Environment :: Console
Classifier: License :: OSI Approved :: GNU General Public License (GPL)
Classifier: Operating System :: OS Independent
Classifier: Programming Language :: Python
Classifier: Topic :: System :: Archiving
Classifier: Topic :: Text Processing :: Indexing
